bischoff_and_ratcliff_1995/Instance.py
bischoff_and_ratcliff_1995/Random.py
bischoff_and_ratcliff_1995/__init__.py
bischoff_and_ratcliff_1995-0.1.0.data/scripts/generate_all_instances
bischoff_and_ratcliff_1995-0.1.0.dist-info/LICENSE
bischoff_and_ratcliff_1995-0.1.0.dist-info/METADATA
bischoff_and_ratcliff_1995-0.1.0.dist-info/WHEEL
bischoff_and_ratcliff_1995-0.1.0.dist-info/top_level.txt
bischoff_and_ratcliff_1995-0.1.0.dist-info/RECORD
